{
  "stockSystem": {
    "enabled": true,
    "timezone": "Asia/Taipei",
    "marketOpenHour": 9,
    "marketCloseHour": 21,
    "tickCronSchedule": "*/5 * * * *",
    "tickIntervalMinutes": 5,
    "openCronSchedule": "0 9 * * *",
    "closeCronSchedule": "0 21 * * *",
    "announceChannelId": "1505072010949169312",
    "reportChannelId": "1505072010949169312",
    "broadcastChannelId": "1505072010949169312",
    "feeRate": 0.01,
    "minFee": 5,
    "maxSharesPerUser": 500,
    "defaultMarketSentiment": "sideways",
    "marketDrift": {
      "bull": 0.001,
      "bear": -0.001,
      "sideways": 0
    },
    "chart": {
      "historyPoints": 20
    },
    "dividend": {
      "enabled": true,
      "cronSchedule": "0 9 * * 1",
      "timezone": "Asia/Taipei",
      "weeksPerYear": 52,
      "minPayoutPerHolder": 1
    },
    "pool": [
      {
        "symbol": "TSPP",
        "name": "嗶積電",
        "initialPrice": 500,
        "sigma": 0.04,
        "floor": 100,
        "type": "tech",
        "dividendYield": 0.02
      },
      {
        "symbol": "UPPI",
        "name": "統嗶超商",
        "initialPrice": 300,
        "sigma": 0.015,
        "floor": 60,
        "type": "blue",
        "dividendYield": 0.04
      },
      {
        "symbol": "EGPP",
        "name": "嗶嗶海運",
        "initialPrice": 120,
        "sigma": 0.08,
        "floor": 20,
        "type": "meme",
        "dividendYield": 0
      },
      {
        "symbol": "CTPP",
        "name": "嗶嗶金控",
        "initialPrice": 800,
        "sigma": 0.025,
        "floor": 160,
        "type": "blue",
        "dividendYield": 0.05
      },
      {
        "symbol": "MTKP",
        "name": "嗶發科",
        "initialPrice": 200,
        "sigma": 0.055,
        "floor": 40,
        "type": "tech",
        "dividendYield": 0.025
      }
    ]
  }
}
